{
  "kind": "singleType",
  "collectionName": "contactos",
  "info": {
    "singularName": "contacto",
    "pluralName": "contactos",
    "displayName": "Contacto",
    "description": ""
  },
  "options": {
    "draftAndPublish": true
  },
  "pluginOptions": {},
  "attributes": {
    "telefono": {
      "type": "string"
    },
    "direccion": {
      "type": "string"
    },
    "horarios": {
      "displayName": "horario",
      "type": "component",
      "repeatable": true,
      "component": "contacto-page.horario"
    },
    "correo": {
      "type": "email"
    },
    "coordenadas": {
      "type": "json"
    }
  }
}
